.bumpversion.cfg
.gitignore
.gitlab-ci.yml
Changelog.md
HACKING.md
LICENSE
README.md
requirements.txt
run_tests.py
setup.py
tox.ini
.githooks/pre-commit
.githooks/pre-push
.github/workflows/tox.yml
fake/common/djangoapps/student/__init__.py
fake/common/djangoapps/student/models.py
fake/course/__init__.py
hastexo/__init__.py
hastexo/admin.py
hastexo/common.py
hastexo/gcloud.py
hastexo/hastexo.py
hastexo/jobs.py
hastexo/models.py
hastexo/openstack.py
hastexo/provider.py
hastexo/tasks.py
hastexo/locale/config.yaml
hastexo/locale/en/LC_MESSAGES/django-partial.po
hastexo/management/__init__.py
hastexo/management/__pycache__/__init__.cpython-310.pyc
hastexo/management/__pycache__/__init__.cpython-311.pyc
hastexo/management/__pycache__/__init__.cpython-312.pyc
hastexo/management/__pycache__/__init__.cpython-38.pyc
hastexo/management/__pycache__/__init__.cpython-39.pyc
hastexo/management/commands/__init__.py
hastexo/management/commands/reaper.py
hastexo/management/commands/suspender.py
hastexo/management/commands/__pycache__/__init__.cpython-310.pyc
hastexo/management/commands/__pycache__/__init__.cpython-311.pyc
hastexo/management/commands/__pycache__/__init__.cpython-312.pyc
hastexo/management/commands/__pycache__/__init__.cpython-38.pyc
hastexo/management/commands/__pycache__/__init__.cpython-39.pyc
hastexo/management/commands/__pycache__/reaper.cpython-310.pyc
hastexo/management/commands/__pycache__/reaper.cpython-311.pyc
hastexo/management/commands/__pycache__/reaper.cpython-312.pyc
hastexo/management/commands/__pycache__/reaper.cpython-38.pyc
hastexo/management/commands/__pycache__/reaper.cpython-39.pyc
hastexo/management/commands/__pycache__/suspender.cpython-310.pyc
hastexo/management/commands/__pycache__/suspender.cpython-311.pyc
hastexo/management/commands/__pycache__/suspender.cpython-312.pyc
hastexo/management/commands/__pycache__/suspender.cpython-38.pyc
hastexo/management/commands/__pycache__/suspender.cpython-39.pyc
hastexo/migrations/0001_initial.py
hastexo_xblock.egg-info/PKG-INFO
hastexo_xblock.egg-info/SOURCES.txt
hastexo_xblock.egg-info/dependency_links.txt
hastexo_xblock.egg-info/entry_points.txt
hastexo_xblock.egg-info/requires.txt
hastexo_xblock.egg-info/top_level.txt
