Metadata-Version: 2.4
Name: hastexo-xblock
Version: 8.5.0
Summary: hastexo XBlock: Makes arbitrarily complex lab environments available on an Open edX LMS
Home-page: https://github.com/hastexo/hastexo-xblock
Author: hastexo
Author-email: pypi@hastexo.com
License: AGPL-3.0
Classifier: Development Status :: 4 - Beta
Classifier: Environment :: OpenStack
Classifier: Framework :: Django
Classifier: Intended Audience :: Education
Classifier: License :: OSI Approved :: GNU Affero General Public License v3
Classifier: Operating System :: POSIX :: Linux
Classifier: Topic :: Education :: Computer Aided Instruction (CAI)
Classifier: Topic :: Education
Requires-Python: >=3.11
License-File: LICENSE
Requires-Dist: apscheduler<4
Requires-Dist: cliff<=4.7
Requires-Dist: dogpile.cache<=1.3
Requires-Dist: google-api-python-client<=2.167.0
Requires-Dist: keystoneauth1<=5.8
Requires-Dist: openstacksdk<=4.1
Requires-Dist: osc-lib<=3.1
Requires-Dist: os-client-config<=2.1
Requires-Dist: oslo.serialization<=5.5
Requires-Dist: oslo.utils<=7.4
Requires-Dist: oslo.config<=9.7.1
Requires-Dist: paramiko<4,>=3.5.0
Requires-Dist: python-heatclient<=4.0
Requires-Dist: python-keystoneclient<=5.5
Requires-Dist: python-novaclient<=18.7
Requires-Dist: tenacity<=9.0
Dynamic: author
Dynamic: author-email
Dynamic: classifier
Dynamic: description
Dynamic: description-content-type
Dynamic: home-page
Dynamic: license
Dynamic: license-file
Dynamic: requires-dist
Dynamic: requires-python
Dynamic: summary
